{
  "basics": {
    "name": "Olyann Ta'ase",
    "label": "Student",
    "picture": "https://techfolios.github.io/template/images/molly.png",
    "email": "olyann.taase@student.chaminade.edu",
    "phone": "",
    "website": "https://otaase.github.io",
    "summary": "I am a first-year Chaminade University student studying in data science. I intend to study here for four years to complete my Bachelor's degree",
    "location": {
      "address": " 3140 Waialae Ave",
      "postalCode": "96816",
      "city": "Honolulu",
      "countryCode": "USA",
      "region": "Hawaii"
    },
    "profiles": [
      {
        "network": "github",
        "username": "otaase",
        "url": "http://github.com/changeme"
      },
      {
        "",
        "username": "otaase",
        "url": "http://linkedin.com/in/changeme"
      },
      {
        "",
        "",
        ""
      },
      {
        "network": "instagram",
        "username": "ataase",
        "url": "http://instagram.com/changeme"
      }
    ]
  },
  "interests": [
    {
      "name": "",
      "": [
        "",
        ""
      ]
    },
    {
      "name": "data mining",
      "k": [
      ]
    },
    {
      "name": "artificial intelligence",
      "keywords": [
      ]
    }
  ],
  "skills": [
    {
      "name": "Languages and Frameworks",
      "level": "",
      "keywords": [
        "",
        "",
        "",
        "",
        "",
        ""
      ]
    },
    {
      "name": "Toolsets/OS",
      "level": "",
      "keywords": [
        "",
        "",
        "",
        "",
        ""
      ]
    }
  ],
  "education": [
    {
      "institution": " Chaminade University, Honolulu, HI",
      "area": " Data Science (expected Spring, 2025 ",
      "studyType": "B.S.",
      "startDate": "2021-08-23",
      "endDate": "Present",
      "gpa": "",
      "courses": [
      ]
    }
  ],
  "work": [
    {
      "company": "",
      "position": "",
      "website": "",
      "startDate": "",
      "endDate": "",
      "summary": "",
      "highlights": [
        "",
        ""
      ]
    },
    {
      "company": "",
      "position": "",
      "website": "",
      "startDate": "",
      "endDate": "",
      "summary": "",
      "highlights": [
        "",
        ""
      ]
    }
  ],
  "volunteer": [
    {
      "organization": "",
      "website": "",
      "position": "",
      "startDate": "",
      "endDate": "",
      "summary": "",
      "highlights": [
        "",
        ""
      ]
    },
    {
      "organization": "",
      "website": "",
      "position": "",
      "startDate": "",
      "endDate": "",
      "summary": "",
      "highlights": [
        "",
        "",
        ""
      ]
    }
  ],
  "awards": [
    {
      "title": "",
      "date": "",
      "awarder": "",
      "summary": ""
    },
    {
      "title": "",
      "date": "",
      "awarder": "",
      "summary": ""
    }
  ],
  "references": [
    {
      "name": "Available upon request",
      "reference": ""
    }
  ]
}
